occtre/__init__.py
occtre/__main__.py
occtre/configuration/__init__.py
occtre/configuration/configuration.py
occtre/configuration/syncer.py
occtre/configuration/templates/dmon_sparc.toml
occtre/configuration/templates/qemu_ppc.toml
occtre/configuration/templates/qemu_sparc.toml
occtre/configuration/templates/sis_sparc.toml
occtre/interface/__init__.py
occtre/interface/coverage_tracer.py
occtre/intern/__init__.py
occtre/intern/address2line.py
occtre/intern/address_hit.py
occtre/intern/architecture/__init__.py
occtre/intern/architecture/architecture.py
occtre/intern/architecture/arm.py
occtre/intern/architecture/msp430.py
occtre/intern/architecture/ppc.py
occtre/intern/architecture/sparc_v8.py
occtre/intern/architecture/x86.py
occtre/intern/disassembler/__init__.py
occtre/intern/disassembler/disassembler.py
occtre/intern/disassembler/sparc_v8.py
occtre/intern/disassembly.py
occtre/intern/logger.py
occtre/intern/parser.py
occtre/intern/process.py
occtre/intern/recorder/__init__.py
occtre/intern/recorder/data_coverage.py
occtre/intern/recorder/instruction_coverage.py
occtre/intern/recorder/recorder.py
occtre/intern/recorder/recorder_factory.py
occtre/intern/table_exporter.py
occtre-0.10.0.dist-info/COPYING.md
occtre-0.10.0.dist-info/LICENSES/GTDGmbH.md
occtre-0.10.0.dist-info/METADATA
occtre-0.10.0.dist-info/WHEEL
occtre-0.10.0.dist-info/entry_points.txt
occtre-0.10.0.dist-info/RECORD
