Metadata-Version: 2.3
Name: occtre
Version: 0.10.0
Summary: A tool for producing, collecting and analyzing test coverage on assembler level
License: MPL-2.0
Keywords: Target,Coverage,Coverage Tracer,Category A
Author: Christoph Weiss
Author-email: christoph.weiss@gtd-gmbh.de
Maintainer: Christoph Weiss
Maintainer-email: christoph.weiss@gtd-gmbh.de
Requires-Python: >=3.10
Classifier: License :: OSI Approved
Classifier: Programming Language :: Python :: 3
Classifier: Programming Language :: Python :: 3.10
Classifier: Programming Language :: Python :: 3.11
Classifier: Programming Language :: Python :: 3.12
Classifier: Programming Language :: Python :: 3.13
Requires-Dist: dataclass_binder (>=0.3.4,<0.4.0)
Requires-Dist: tabulate (>=0.9.0,<0.10.0)
Requires-Dist: tomlkit (>=0.12.3,<0.13.0)
Project-URL: Homepage, https://gtd-gmbh.de/
